pysuez/__init__.py
pysuez/__main__.py
pysuez/client.py
pysuez-0.2.0.dist-info/LICENSE
pysuez-0.2.0.dist-info/METADATA
pysuez-0.2.0.dist-info/WHEEL
pysuez-0.2.0.dist-info/entry_points.txt
pysuez-0.2.0.dist-info/top_level.txt
pysuez-0.2.0.dist-info/RECORD
