Metadata-Version: 2.1
Name: pysuez
Version: 0.2.0
Summary: Get your water consumption data from your Suez account (www.toutsurmoneau.fr and its sub-providers)
Home-page: https://github.com/ooii/pySuez
Download-URL: https://github.com/ooii/pySuez/releases/tag/0.2.0
Author: Farid N27
Author-email: pySuezWater@ooii.io
License: Apache 2.0
Classifier: Programming Language :: Python :: 3.4
Classifier: Programming Language :: Python :: 3.5
Classifier: Programming Language :: Python :: 3.6
Classifier: Programming Language :: Python :: 3.7
Classifier: Programming Language :: Python :: 3.8
Classifier: Programming Language :: Python :: 3.9
License-File: LICENSE
Requires-Dist: regex
Requires-Dist: requests
Requires-Dist: datetime
